[
    {
        "id": "0",
        "vault": "BearosSnap",
        "total": "-97",
        "today": "-12",
        "activeDays": "712",
        "follower": "7",
        "equity": "12000",
        "performanceData": [
            {
                "date": "2023-08-01",
                "value": 1000
            },
            {
                "date": "2023-08-02",
                "value": 1050
            },
            {
                "date": "2023-08-03",
                "value": 1100
            },
            {
                "date": "2023-08-04",
                "value": 100
            },
            {
                "date": "2023-08-05",
                "value": 1050
            },
            {
                "date": "2023-08-06",
                "value": 1200
            }
        ]
    },
    {
        "id": "1",
        "vault": "BTC TDM",
        "total": "+212",
        "today": "+12",
        "activeDays": "41",
        "follower": "2",
        "equity": "114000",
        "performanceData": [
            {
                "date": "2023-08-01",
                "value": 1000
            },
            {
                "date": "2023-08-02",
                "value": 1050
            },
            {
                "date": "2023-08-03",
                "value": 1100
            }
        ]
    },
    {
        "id": "2",
        "vault": "ETH TDM",
        "total": "+2",
        "today": "+8",
        "activeDays": "3",
        "follower": "10",
        "equity": "12",
        "performanceData": [
            {
                "date": "2023-08-01",
                "value": 1000
            },
            {
                "date": "2023-08-02",
                "value": 1050
            },
            {
                "date": "2023-08-03",
                "value": 1100
            }
        ]
    }
]